aiida_project/__init__.py
aiida_project/config.py
aiida_project/shell.py
aiida_project/commands/__init__.py
aiida_project/commands/main.py
aiida_project/data/__init__.py
aiida_project/data/shell_fields.yaml
aiida_project/project/__init__.py
aiida_project/project/base.py
aiida_project/project/conda.py
aiida_project/project/core.py
aiida_project/project/venv.py
aiida_project-0.6.0.dist-info/entry_points.txt
aiida_project-0.6.0.dist-info/licenses/LICENSE.txt
aiida_project-0.6.0.dist-info/WHEEL
aiida_project-0.6.0.dist-info/METADATA
aiida_project-0.6.0.dist-info/RECORD
