Metadata-Version: 2.4
Name: aiida-project
Version: 0.6.0
Summary: An AiiDA environment manager
Keywords: aiida,workflows
Author-email: The AiiDA team <developers@aiida.net>
Requires-Python: >=3.8
Classifier: Development Status :: 2 - Pre-Alpha
Classifier: Framework :: AiiDA
Classifier: License :: OSI Approved :: MIT License
Classifier: Operating System :: POSIX :: Linux
Classifier: Operating System :: MacOS :: MacOS X
Classifier: Programming Language :: Python
Classifier: Programming Language :: Python :: 3.8
Classifier: Programming Language :: Python :: 3.9
Classifier: Programming Language :: Python :: 3.10
Classifier: Programming Language :: Python :: 3.11
Classifier: Topic :: Scientific/Engineering
License-File: LICENSE.txt
Requires-Dist: py~=1.11
Requires-Dist: pydantic~=2.7
Requires-Dist: pydantic-settings~=2.2
Requires-Dist: python-dotenv~=1.0
Requires-Dist: typer[all]~=0.9
Requires-Dist: pyyaml~=6.0
Requires-Dist: pre-commit~=3.2.2 ; extra == "dev"
Project-URL: Source, https://github.com/aiidateam/aiida-project
Provides-Extra: dev
